linovelib2epub/__about__.py
linovelib2epub/__init__.py
linovelib2epub/exceptions.py
linovelib2epub/linovel.py
linovelib2epub/logger.py
linovelib2epub/models.py
linovelib2epub/settings.py
linovelib2epub/utils.py
linovelib2epub/spider/__init__.py
linovelib2epub/spider/base_spider.py
linovelib2epub/spider/linovelib_mobile_spider.py
linovelib2epub/styles/chapter.css
linovelib2epub/styles/cover.css
linovelib2epub/styles/nav.css
linovelib2epub-0.1.3.dist-info/METADATA
linovelib2epub-0.1.3.dist-info/WHEEL
linovelib2epub-0.1.3.dist-info/licenses/LICENSE
linovelib2epub-0.1.3.dist-info/RECORD
