Metadata-Version: 2.1
Name: linovelib2epub
Version: 0.1.3
Summary: Craw light novel from [哔哩轻小说(linovelib)](https://w.linovelib.com/) and convert to epub.
Project-URL: Homepage, https://github.com/wdpm/linovelib2epub
Project-URL: Source, https://github.com/wdpm/linovelib2epub
Project-URL: Tracker, https://github.com/wdpm/linovelib2epub/issues
Author-email: wdpm <1137299673@qq.com>
License-File: LICENSE
Keywords: ebook,epub,library,light novel,哔哩轻小说
Classifier: Development Status :: 3 - Alpha
Classifier: Intended Audience :: Developers
Classifier: License :: OSI Approved :: GNU Affero General Public License v3 or later (AGPLv3+)
Classifier: Natural Language :: Chinese (Simplified)
Classifier: Natural Language :: Chinese (Traditional)
Classifier: Operating System :: OS Independent
Classifier: Programming Language :: Python :: 3
Classifier: Programming Language :: Python :: 3.8
Classifier: Programming Language :: Python :: 3.9
Classifier: Programming Language :: Python :: 3.10
Classifier: Programming Language :: Python :: 3.11
Classifier: Topic :: Software Development :: Libraries
Requires-Python: >=3.8
Requires-Dist: aiofiles>=23.1.0
Requires-Dist: aiohttp>=3.8.4
Requires-Dist: bs4>=0.0.1
Requires-Dist: demjson3>=3.0.5
Requires-Dist: ebooklib>=0.17.1
Requires-Dist: fake-useragent>=1.1.1
Requires-Dist: inquirer>=3.1.2
Requires-Dist: pillow>=9.2.0
Requires-Dist: requests>=2.28.1
Requires-Dist: rich>=12.5.1
Requires-Dist: uuid>=1.30
